odoo10_addon_l10n_br_sale_stock-10.0.1.0.0.99.dev16-py3.8-nspkg.pth
odoo/addons/l10n_br_sale_stock/README.rst
odoo/addons/l10n_br_sale_stock/__init__.py
odoo/addons/l10n_br_sale_stock/__manifest__.py
odoo/addons/l10n_br_sale_stock/demo/l10n_br_sale_stock_demo.xml
odoo/addons/l10n_br_sale_stock/i18n/pt_BR.po
odoo/addons/l10n_br_sale_stock/models/__init__.py
odoo/addons/l10n_br_sale_stock/models/procurement.py
odoo/addons/l10n_br_sale_stock/models/sale.py
odoo/addons/l10n_br_sale_stock/models/stock_account.py
odoo/addons/l10n_br_sale_stock/readme/CONFIGURE.rst
odoo/addons/l10n_br_sale_stock/readme/CONTRIBUTORS.rst
odoo/addons/l10n_br_sale_stock/readme/CREDITS.rst
odoo/addons/l10n_br_sale_stock/readme/DESCRIPTION.rst
odoo/addons/l10n_br_sale_stock/readme/HISTORY.rst
odoo/addons/l10n_br_sale_stock/readme/INSTALL.rst
odoo/addons/l10n_br_sale_stock/readme/ROADMAP.rst
odoo/addons/l10n_br_sale_stock/readme/USAGE.rst
odoo/addons/l10n_br_sale_stock/security/ir.model.access.csv
odoo/addons/l10n_br_sale_stock/static/description/icon.png
odoo/addons/l10n_br_sale_stock/static/description/index.html
odoo/addons/l10n_br_sale_stock/tests/__init__.py
odoo/addons/l10n_br_sale_stock/tests/test_l10n_br_sale_stock.py
odoo/addons/l10n_br_sale_stock/views/sale_stock_view.xml
odoo/addons/l10n_br_sale_stock/wizard/__init__.py
odoo/addons/l10n_br_sale_stock/wizard/stock_invoice_onshipping.py
odoo10_addon_l10n_br_sale_stock-10.0.1.0.0.99.dev16.dist-info/METADATA
odoo10_addon_l10n_br_sale_stock-10.0.1.0.0.99.dev16.dist-info/WHEEL
odoo10_addon_l10n_br_sale_stock-10.0.1.0.0.99.dev16.dist-info/namespace_packages.txt
odoo10_addon_l10n_br_sale_stock-10.0.1.0.0.99.dev16.dist-info/top_level.txt
odoo10_addon_l10n_br_sale_stock-10.0.1.0.0.99.dev16.dist-info/RECORD
