Metadata-Version: 2.1
Name: odoo10-addon-l10n-br-sale-stock
Version: 10.0.1.0.0.99.dev16
Summary: Brazilian Localization Sales and Warehouse
Home-page: http://odoo-brasil.org
Author: Akretion, ,Odoo Community Association (OCA)
Author-email: support@odoo-community.org
License: AGPL-3
Platform: UNKNOWN
Classifier: Programming Language :: Python
Classifier: Framework :: Odoo
Classifier: Framework :: Odoo :: 10.0
Classifier: License :: OSI Approved :: GNU Affero General Public License v3
Requires-Python: ~=2.7
Requires-Dist: odoo10-addon-account-fiscal-position-rule-sale-stock
Requires-Dist: odoo10-addon-l10n-br-sale-product
Requires-Dist: odoo10-addon-l10n-br-stock-account
Requires-Dist: odoo <10.1dev,>=10.0
